reyserver/__init__.py
reyserver/rall.py
reyserver/rauth.py
reyserver/rbase.py
reyserver/rbind.py
reyserver/rcache.py
reyserver/rclient.py
reyserver/rfile.py
reyserver/rpublic.py
reyserver/rredirect.py
reyserver/rserver.py
reyserver/rtest.py
reyserver-1.1.92.dist-info/METADATA
reyserver-1.1.92.dist-info/WHEEL
reyserver-1.1.92.dist-info/licenses/LICENSE
reyserver-1.1.92.dist-info/RECORD
