Metadata-Version: 2.4
Name: reyserver
Version: 1.1.92
Summary: Backend server method set.
Project-URL: homepage, https://github.com/reyxbo/reyserver/
Author-email: Rey <reyxbo@163.com>
License: Copyright 2025 ReyXBo
License-File: LICENSE
Keywords: API,async,asynchronous,backend,rey,reyxbo,server
Requires-Python: >=3.12
Requires-Dist: fastapi-cache2[redis]
Requires-Dist: fastapi[standard]
Requires-Dist: reydb
Requires-Dist: reykit
Requires-Dist: sqladmin[full]
Requires-Dist: uvicorn[standard]
